rally/__init__.py
rally/_rate_limit.py
rally/_session.py
rally/_storage.py
rally/_utils.py
rally/asset.py
rally/context.py
rally/exceptions.py
rally/files.py
rally/jobs.py
rally/notifications.py
rally/secret.py
rally/supplyChain.py
rally/userDefinedConnector.py
rally/_vendored/__init__.py
rally/_vendored/__pycache__/__init__.cpython-310.pyc
rally/_vendored/bin/chardetect
rally/_vendored/certifi/__init__.py
rally/_vendored/certifi/__main__.py
rally/_vendored/certifi/cacert.pem
rally/_vendored/certifi/core.py
rally/_vendored/certifi/py.typed
rally/_vendored/chardet/__init__.py
rally/_vendored/chardet/__main__.py
rally/_vendored/chardet/big5freq.py
rally/_vendored/chardet/big5prober.py
rally/_vendored/chardet/chardistribution.py
rally/_vendored/chardet/charsetgroupprober.py
rally/_vendored/chardet/charsetprober.py
rally/_vendored/chardet/codingstatemachine.py
rally/_vendored/chardet/codingstatemachinedict.py
rally/_vendored/chardet/cp949prober.py
rally/_vendored/chardet/enums.py
rally/_vendored/chardet/escprober.py
rally/_vendored/chardet/escsm.py
rally/_vendored/chardet/eucjpprober.py
rally/_vendored/chardet/euckrfreq.py
rally/_vendored/chardet/euckrprober.py
rally/_vendored/chardet/euctwfreq.py
rally/_vendored/chardet/euctwprober.py
rally/_vendored/chardet/gb2312freq.py
rally/_vendored/chardet/gb2312prober.py
rally/_vendored/chardet/hebrewprober.py
rally/_vendored/chardet/jisfreq.py
rally/_vendored/chardet/johabfreq.py
rally/_vendored/chardet/johabprober.py
rally/_vendored/chardet/jpcntx.py
rally/_vendored/chardet/langbulgarianmodel.py
rally/_vendored/chardet/langgreekmodel.py
rally/_vendored/chardet/langhebrewmodel.py
rally/_vendored/chardet/langhungarianmodel.py
rally/_vendored/chardet/langrussianmodel.py
rally/_vendored/chardet/langthaimodel.py
rally/_vendored/chardet/langturkishmodel.py
rally/_vendored/chardet/latin1prober.py
rally/_vendored/chardet/macromanprober.py
rally/_vendored/chardet/mbcharsetprober.py
rally/_vendored/chardet/mbcsgroupprober.py
sdvi_rally-1.12.0.dist-info/licenses/LICENSE
rally/_vendored/certifi-2023.7.22.dist-info/INSTALLER
rally/_vendored/certifi-2023.7.22.dist-info/LICENSE
rally/_vendored/certifi-2023.7.22.dist-info/METADATA
rally/_vendored/certifi-2023.7.22.dist-info/RECORD
rally/_vendored/certifi-2023.7.22.dist-info/REQUESTED
rally/_vendored/certifi-2023.7.22.dist-info/WHEEL
rally/_vendored/certifi-2023.7.22.dist-info/top_level.txt
rally/_vendored/chardet-5.2.0.dist-info/INSTALLER
rally/_vendored/chardet-5.2.0.dist-info/LICENSE
rally/_vendored/chardet-5.2.0.dist-info/METADATA
rally/_vendored/chardet-5.2.0.dist-info/RECORD
rally/_vendored/chardet-5.2.0.dist-info/REQUESTED
rally/_vendored/chardet-5.2.0.dist-info/WHEEL
rally/_vendored/chardet-5.2.0.dist-info/entry_points.txt
rally/_vendored/chardet-5.2.0.dist-info/top_level.txt
rally/_vendored/idna-3.6.dist-info/INSTALLER
rally/_vendored/idna-3.6.dist-info/LICENSE.md
rally/_vendored/idna-3.6.dist-info/METADATA
rally/_vendored/idna-3.6.dist-info/RECORD
rally/_vendored/idna-3.6.dist-info/REQUESTED
rally/_vendored/idna-3.6.dist-info/WHEEL
rally/_vendored/requests-2.32.3.dist-info/INSTALLER
rally/_vendored/requests-2.32.3.dist-info/LICENSE
rally/_vendored/requests-2.32.3.dist-info/METADATA
rally/_vendored/requests-2.32.3.dist-info/RECORD
rally/_vendored/requests-2.32.3.dist-info/REQUESTED
rally/_vendored/requests-2.32.3.dist-info/WHEEL
rally/_vendored/requests-2.32.3.dist-info/top_level.txt
rally/_vendored/urllib3-1.26.18.dist-info/INSTALLER
rally/_vendored/urllib3-1.26.18.dist-info/LICENSE.txt
rally/_vendored/urllib3-1.26.18.dist-info/METADATA
rally/_vendored/urllib3-1.26.18.dist-info/RECORD
rally/_vendored/urllib3-1.26.18.dist-info/REQUESTED
rally/_vendored/urllib3-1.26.18.dist-info/WHEEL
rally/_vendored/urllib3-1.26.18.dist-info/top_level.txt
sdvi_rally-1.12.0.dist-info/METADATA
sdvi_rally-1.12.0.dist-info/WHEEL
sdvi_rally-1.12.0.dist-info/entry_points.txt
sdvi_rally-1.12.0.dist-info/top_level.txt
sdvi_rally-1.12.0.dist-info/RECORD
