Metadata-Version: 2.4
Name: sdvi-rally
Version: 1.12.0
Summary: Rally Python SDK
Author: SDVI Corp
License: Proprietary
Classifier: Programming Language :: Python :: 3.6
Classifier: License :: Other/Proprietary License
Classifier: Operating System :: OS Independent
Requires-Python: >=3.6
License-File: LICENSE
Requires-Dist: Click
Requires-Dist: certifi
Dynamic: author
Dynamic: classifier
Dynamic: description
Dynamic: description-content-type
Dynamic: license
Dynamic: license-file
Dynamic: requires-dist
Dynamic: requires-python
Dynamic: summary
